canedge_http/__init__.py
canedge_http/canedge_http.py
canedge_http/tools/__init__.py
canedge_http/tools/tool_download_log_files.py
canedge_http-0.0.3.dist-info/METADATA
canedge_http-0.0.3.dist-info/WHEEL
canedge_http-0.0.3.dist-info/entry_points.txt
canedge_http-0.0.3.dist-info/RECORD
