Metadata-Version: 2.4
Name: CANedge-HTTP
Version: 0.0.3
Summary: Python module for accessing CANEdge filesystem via HTTP
Project-URL: Homepage, https://www.csselectronics.com/
Author: CSS Electronics
Author-email: contact@csselectronics.com
License: MIT
Keywords: CANEdge,CSS Electronics
Classifier: License :: OSI Approved :: MIT License
Classifier: Operating System :: OS Independent
Classifier: Programming Language :: Python :: 3
Requires-Python: >=3.7
Requires-Dist: requests>=2.32.3
